jump_and_run_game/__init__.py
jump_and_run_game/_version.py
jump_and_run_game-0.0.1.dist-info/entry_points.txt
jump_and_run_game-0.0.1.dist-info/LICENSE
jump_and_run_game-0.0.1.dist-info/WHEEL
jump_and_run_game-0.0.1.dist-info/METADATA
jump_and_run_game-0.0.1.dist-info/RECORD
